apiratelimit/__init__.py
apiratelimit/decorators.py
apiratelimit/exception.py
apiratelimit/utils.py
apiratelimit-2.2.1.dist-info/LICENSE.txt
apiratelimit-2.2.1.dist-info/METADATA
apiratelimit-2.2.1.dist-info/WHEEL
apiratelimit-2.2.1.dist-info/top_level.txt
apiratelimit-2.2.1.dist-info/RECORD
