Metadata-Version: 2.1
Name: apiratelimit
Version: 2.2.1
Summary: API rate limit decorator
Home-page: https://github.com/chiragkanhasoft/apiratelimit
Author: Tomas Basham
Author-email: me@tomasbasham.co.uk
License: MIT
Keywords: ratelimit,api,decorator
Platform: UNKNOWN
Classifier: Development Status :: 5 - Production/Stable
Classifier: Intended Audience :: Developers
Classifier: License :: OSI Approved :: MIT License
Classifier: Natural Language :: English
Classifier: Programming Language :: Python
Classifier: Topic :: Software Development
License-File: LICENSE.txt
